{
  "externalControllerServices" : { },
  "flow" : {
    "createdTimestamp" : 1752649619869,
    "description" : "",
    "identifier" : "alluebungen",
    "lastModifiedTimestamp" : 1752649619869,
    "name" : "all_uebungen",
    "versionCount" : 0
  },
  "flowContents" : {
    "comments" : "",
    "componentType" : "PROCESS_GROUP",
    "connections" : [ ],
    "controllerServices" : [ ],
    "defaultBackPressureDataSizeThreshold" : "1 GB",
    "defaultBackPressureObjectThreshold" : 10000,
    "defaultFlowFileExpiration" : "0 sec",
    "executionEngine" : "INHERITED",
    "externalControllerServiceReferences" : { },
    "flowFileConcurrency" : "UNBOUNDED",
    "flowFileOutboundPolicy" : "STREAM_WHEN_AVAILABLE",
    "funnels" : [ ],
    "identifier" : "flow-contents-group",
    "inputPorts" : [ ],
    "labels" : [ ],
    "maxConcurrentTasks" : 1,
    "name" : "uebungen",
    "outputPorts" : [ ],
    "position" : {
      "x" : 0.0,
      "y" : 0.0
    },
    "processGroups" : [ {
      "comments" : "",
      "componentType" : "PROCESS_GROUP",
      "connections" : [ ],
      "controllerServices" : [ ],
      "defaultBackPressureDataSizeThreshold" : "1 GB",
      "defaultBackPressureObjectThreshold" : 10000,
      "defaultFlowFileExpiration" : "0 sec",
      "executionEngine" : "INHERITED",
      "flowFileConcurrency" : "UNBOUNDED",
      "flowFileOutboundPolicy" : "STREAM_WHEN_AVAILABLE",
      "funnels" : [ ],
      "groupIdentifier" : "flow-contents-group",
      "identifier" : "28642ea8-0546-3952-a9a6-d77eba616e08",
      "inputPorts" : [ ],
      "labels" : [ ],
      "maxConcurrentTasks" : 1,
      "name" : "uebung01",
      "outputPorts" : [ ],
      "position" : {
        "x" : 1390.0375515542664,
        "y" : -1743.6490213648226
      },
      "processGroups" : [ ],
      "processors" : [ ],
      "remoteProcessGroups" : [ ],
      "scheduledState" : "ENABLED",
      "statelessFlowTimeout" : "1 min",
      "versionedFlowCoordinates" : {
        "branch" : "main",
        "bucketId" : "uebungen",
        "flowId" : "uebungen-01",
        "storageLocation" : "git@github.com:mhlOrdix/nifiDataFlows.git",
        "version" : "0090a7e939c0d686eda8864f35e3122caf993cd7"
      }
    }, {
      "comments" : "",
      "componentType" : "PROCESS_GROUP",
      "connections" : [ ],
      "controllerServices" : [ ],
      "defaultBackPressureDataSizeThreshold" : "1 GB",
      "defaultBackPressureObjectThreshold" : 10000,
      "defaultFlowFileExpiration" : "0 sec",
      "executionEngine" : "INHERITED",
      "flowFileConcurrency" : "UNBOUNDED",
      "flowFileOutboundPolicy" : "STREAM_WHEN_AVAILABLE",
      "funnels" : [ ],
      "groupIdentifier" : "flow-contents-group",
      "identifier" : "f9472d28-e656-313e-b999-072f3435e89e",
      "inputPorts" : [ ],
      "labels" : [ ],
      "maxConcurrentTasks" : 1,
      "name" : "uebung02",
      "outputPorts" : [ ],
      "position" : {
        "x" : 1832.0,
        "y" : -1744.0
      },
      "processGroups" : [ ],
      "processors" : [ ],
      "remoteProcessGroups" : [ ],
      "scheduledState" : "ENABLED",
      "statelessFlowTimeout" : "1 min",
      "versionedFlowCoordinates" : {
        "branch" : "main",
        "bucketId" : "uebungen",
        "flowId" : "uebungen-02",
        "storageLocation" : "git@github.com:mhlOrdix/nifiDataFlows.git",
        "version" : "a24b28ba4378072c444b1883900ad192ae6a93c7"
      }
    }, {
      "comments" : "",
      "componentType" : "PROCESS_GROUP",
      "connections" : [ ],
      "controllerServices" : [ ],
      "defaultBackPressureDataSizeThreshold" : "1 GB",
      "defaultBackPressureObjectThreshold" : 10000,
      "defaultFlowFileExpiration" : "0 sec",
      "executionEngine" : "INHERITED",
      "flowFileConcurrency" : "UNBOUNDED",
      "flowFileOutboundPolicy" : "STREAM_WHEN_AVAILABLE",
      "funnels" : [ ],
      "groupIdentifier" : "flow-contents-group",
      "identifier" : "6aa8b230-166f-3881-8b95-d0ec8e8e0ffe",
      "inputPorts" : [ ],
      "labels" : [ ],
      "maxConcurrentTasks" : 1,
      "name" : "uebung03",
      "outputPorts" : [ ],
      "position" : {
        "x" : 2256.0,
        "y" : -1744.0
      },
      "processGroups" : [ ],
      "processors" : [ ],
      "remoteProcessGroups" : [ ],
      "scheduledState" : "ENABLED",
      "statelessFlowTimeout" : "1 min",
      "versionedFlowCoordinates" : {
        "branch" : "main",
        "bucketId" : "uebungen",
        "flowId" : "uebungen-03",
        "storageLocation" : "git@github.com:mhlOrdix/nifiDataFlows.git",
        "version" : "7b19442be521d0054250fed7167cc8052a643f01"
      }
    } ],
    "processors" : [ ],
    "remoteProcessGroups" : [ ],
    "scheduledState" : "ENABLED",
    "statelessFlowTimeout" : "1 min"
  },
  "flowEncodingVersion" : "1.0",
  "latest" : false,
  "parameterContexts" : { },
  "parameterProviders" : { },
  "snapshotMetadata" : {
    "author" : "admin",
    "flowIdentifier" : "alluebungen",
    "timestamp" : 0
  }
}