{
  "externalControllerServices" : {
    "9d510a56-53df-3c2b-b2ff-4e029be87d1e" : {
      "identifier" : "9d510a56-53df-3c2b-b2ff-4e029be87d1e",
      "name" : "MySQL Connection Pool"
    },
    "738f484d-a9db-36f8-8817-07c99dde382b" : {
      "identifier" : "738f484d-a9db-36f8-8817-07c99dde382b",
      "name" : "AvroRecordSetWriter"
    },
    "600c16fd-3584-32ea-bdba-6ec4828f24d8" : {
      "identifier" : "600c16fd-3584-32ea-bdba-6ec4828f24d8",
      "name" : "AvroReader"
    }
  },
  "flow" : {
    "createdTimestamp" : 1754642234616,
    "description" : "",
    "identifier" : "product-data-routing",
    "lastModifiedTimestamp" : 1754642234616,
    "name" : "product-data-routing",
    "versionCount" : 0
  },
  "flowContents" : {
    "comments" : "",
    "componentType" : "PROCESS_GROUP",
    "connections" : [ {
      "backPressureDataSizeThreshold" : "1 GB",
      "backPressureObjectThreshold" : 10000,
      "bends" : [ ],
      "componentType" : "CONNECTION",
      "destination" : {
        "comments" : "",
        "groupId" : "flow-contents-group",
        "id" : "88cee2e4-0198-1000-9e80-4012a3a8f81c",
        "name" : "Funnel",
        "type" : "FUNNEL"
      },
      "flowFileExpiration" : "0 sec",
      "groupIdentifier" : "flow-contents-group",
      "identifier" : "88cee2e9-0198-1000-82e0-8817ac308ad4",
      "labelIndex" : 0,
      "loadBalanceCompression" : "DO_NOT_COMPRESS",
      "loadBalanceStrategy" : "DO_NOT_LOAD_BALANCE",
      "name" : "",
      "partitioningAttribute" : "",
      "prioritizers" : [ ],
      "selectedRelationships" : [ "haushalt" ],
      "source" : {
        "comments" : "",
        "groupId" : "flow-contents-group",
        "id" : "88cee2e0-0198-1000-28f5-1402b00d0d8e",
        "name" : "Produkte nach Kategorie filtern",
        "type" : "PROCESSOR"
      },
      "zIndex" : 17
    }, {
      "backPressureDataSizeThreshold" : "1 GB",
      "backPressureObjectThreshold" : 10000,
      "bends" : [ ],
      "componentType" : "CONNECTION",
      "destination" : {
        "comments" : "",
        "groupId" : "flow-contents-group",
        "id" : "88cee2df-0198-1000-4c31-20c2257eae39",
        "name" : "Avro to JSON",
        "type" : "PROCESSOR"
      },
      "flowFileExpiration" : "0 sec",
      "groupIdentifier" : "flow-contents-group",
      "identifier" : "4458577d-b873-3a50-9a69-0058daf605cd",
      "labelIndex" : 0,
      "loadBalanceCompression" : "DO_NOT_COMPRESS",
      "loadBalanceStrategy" : "DO_NOT_LOAD_BALANCE",
      "name" : "",
      "partitioningAttribute" : "",
      "prioritizers" : [ ],
      "selectedRelationships" : [ "success" ],
      "source" : {
        "comments" : "",
        "groupId" : "flow-contents-group",
        "id" : "509f3256-c305-39f6-a7a8-eb87bdf3c62d",
        "name" : "ExecuteSQL",
        "type" : "PROCESSOR"
      },
      "zIndex" : 18
    }, {
      "backPressureDataSizeThreshold" : "1 GB",
      "backPressureObjectThreshold" : 10000,
      "bends" : [ ],
      "componentType" : "CONNECTION",
      "destination" : {
        "comments" : "",
        "groupId" : "flow-contents-group",
        "id" : "88cee2e2-0198-1000-a141-bd4d6fcadb93",
        "name" : "Funnel",
        "type" : "FUNNEL"
      },
      "flowFileExpiration" : "0 sec",
      "groupIdentifier" : "flow-contents-group",
      "identifier" : "88cee2e7-0198-1000-0948-33b6d1db9881",
      "labelIndex" : 0,
      "loadBalanceCompression" : "DO_NOT_COMPRESS",
      "loadBalanceStrategy" : "DO_NOT_LOAD_BALANCE",
      "name" : "",
      "partitioningAttribute" : "",
      "prioritizers" : [ ],
      "selectedRelationships" : [ "elektronik" ],
      "source" : {
        "comments" : "",
        "groupId" : "flow-contents-group",
        "id" : "88cee2e0-0198-1000-28f5-1402b00d0d8e",
        "name" : "Produkte nach Kategorie filtern",
        "type" : "PROCESSOR"
      },
      "zIndex" : 4
    }, {
      "backPressureDataSizeThreshold" : "1 GB",
      "backPressureObjectThreshold" : 10000,
      "bends" : [ ],
      "componentType" : "CONNECTION",
      "destination" : {
        "comments" : "",
        "groupId" : "flow-contents-group",
        "id" : "88cee2e0-0198-1000-28f5-1402b00d0d8e",
        "name" : "Produkte nach Kategorie filtern",
        "type" : "PROCESSOR"
      },
      "flowFileExpiration" : "0 sec",
      "groupIdentifier" : "flow-contents-group",
      "identifier" : "88cee2e8-0198-1000-7b6b-226ef2528b6d",
      "labelIndex" : 0,
      "loadBalanceCompression" : "DO_NOT_COMPRESS",
      "loadBalanceStrategy" : "DO_NOT_LOAD_BALANCE",
      "name" : "",
      "partitioningAttribute" : "",
      "prioritizers" : [ ],
      "selectedRelationships" : [ "success" ],
      "source" : {
        "comments" : "",
        "groupId" : "flow-contents-group",
        "id" : "88cee2df-0198-1000-4c31-20c2257eae39",
        "name" : "Avro to JSON",
        "type" : "PROCESSOR"
      },
      "zIndex" : 3
    }, {
      "backPressureDataSizeThreshold" : "1 GB",
      "backPressureObjectThreshold" : 10000,
      "bends" : [ ],
      "componentType" : "CONNECTION",
      "destination" : {
        "comments" : "",
        "groupId" : "flow-contents-group",
        "id" : "88cee2e3-0198-1000-80df-c0b19deb92f7",
        "name" : "Funnel",
        "type" : "FUNNEL"
      },
      "flowFileExpiration" : "0 sec",
      "groupIdentifier" : "flow-contents-group",
      "identifier" : "88cee2eb-0198-1000-680a-5d32035ef46e",
      "labelIndex" : 0,
      "loadBalanceCompression" : "DO_NOT_COMPRESS",
      "loadBalanceStrategy" : "DO_NOT_LOAD_BALANCE",
      "name" : "",
      "partitioningAttribute" : "",
      "prioritizers" : [ ],
      "selectedRelationships" : [ "bücher" ],
      "source" : {
        "comments" : "",
        "groupId" : "flow-contents-group",
        "id" : "88cee2e0-0198-1000-28f5-1402b00d0d8e",
        "name" : "Produkte nach Kategorie filtern",
        "type" : "PROCESSOR"
      },
      "zIndex" : 16
    } ],
    "controllerServices" : [ ],
    "defaultBackPressureDataSizeThreshold" : "1 GB",
    "defaultBackPressureObjectThreshold" : 10000,
    "defaultFlowFileExpiration" : "0 sec",
    "executionEngine" : "INHERITED",
    "externalControllerServiceReferences" : {
      "9d510a56-53df-3c2b-b2ff-4e029be87d1e" : {
        "identifier" : "9d510a56-53df-3c2b-b2ff-4e029be87d1e",
        "name" : "MySQL Connection Pool"
      },
      "738f484d-a9db-36f8-8817-07c99dde382b" : {
        "identifier" : "738f484d-a9db-36f8-8817-07c99dde382b",
        "name" : "AvroRecordSetWriter"
      },
      "600c16fd-3584-32ea-bdba-6ec4828f24d8" : {
        "identifier" : "600c16fd-3584-32ea-bdba-6ec4828f24d8",
        "name" : "AvroReader"
      }
    },
    "flowFileConcurrency" : "UNBOUNDED",
    "flowFileOutboundPolicy" : "STREAM_WHEN_AVAILABLE",
    "funnels" : [ {
      "componentType" : "FUNNEL",
      "groupIdentifier" : "flow-contents-group",
      "identifier" : "88cee2e2-0198-1000-a141-bd4d6fcadb93",
      "position" : {
        "x" : -632.1666787875993,
        "y" : 3.8333524744787155
      }
    }, {
      "componentType" : "FUNNEL",
      "groupIdentifier" : "flow-contents-group",
      "identifier" : "88cee2e3-0198-1000-80df-c0b19deb92f7",
      "position" : {
        "x" : -464.16667878759927,
        "y" : 203.83335247447872
      }
    }, {
      "componentType" : "FUNNEL",
      "groupIdentifier" : "flow-contents-group",
      "identifier" : "88cee2e4-0198-1000-9e80-4012a3a8f81c",
      "position" : {
        "x" : -32.16667878759927,
        "y" : 203.83335247447872
      }
    } ],
    "identifier" : "flow-contents-group",
    "inputPorts" : [ ],
    "labels" : [ {
      "componentType" : "LABEL",
      "groupIdentifier" : "flow-contents-group",
      "height" : 72.0,
      "identifier" : "88cee2e6-0198-1000-530c-ebffbc30f544",
      "label" : "Alle Produkte nach Kategorie filtern\n-> QueryRecord",
      "position" : {
        "x" : -384.16667878759927,
        "y" : -92.16664752552128
      },
      "style" : {
        "font-size" : "12px"
      },
      "width" : 176.0,
      "zIndex" : 1
    }, {
      "componentType" : "LABEL",
      "groupIdentifier" : "flow-contents-group",
      "height" : 72.0,
      "identifier" : "88cee2e5-0198-1000-6320-78ad36f2b9c2",
      "label" : "Avro in JSON umwandeln",
      "position" : {
        "x" : 143.83332121240073,
        "y" : -84.16664752552128
      },
      "style" : {
        "font-size" : "12px"
      },
      "width" : 176.0,
      "zIndex" : 1
    } ],
    "maxConcurrentTasks" : 1,
    "name" : "Demo ConvertRecord und QueryRecord",
    "outputPorts" : [ ],
    "position" : {
      "x" : 0.0,
      "y" : 0.0
    },
    "processGroups" : [ ],
    "processors" : [ {
      "autoTerminatedRelationships" : [ "original", "failure" ],
      "backoffMechanism" : "PENALIZE_FLOWFILE",
      "bulletinLevel" : "WARN",
      "bundle" : {
        "artifact" : "nifi-standard-nar",
        "group" : "org.apache.nifi",
        "version" : "2.4.0"
      },
      "comments" : "",
      "componentType" : "PROCESSOR",
      "concurrentlySchedulableTaskCount" : 1,
      "executionNode" : "ALL",
      "groupIdentifier" : "flow-contents-group",
      "identifier" : "88cee2e0-0198-1000-28f5-1402b00d0d8e",
      "maxBackoffPeriod" : "10 mins",
      "name" : "Produkte nach Kategorie filtern",
      "penaltyDuration" : "30 sec",
      "position" : {
        "x" : -344.16667878759927,
        "y" : -44.166647525521284
      },
      "properties" : {
        "dbf-default-precision" : "10",
        "bücher" : "SELECT *\nFROM FLOWFILE\nWHERE Kategorie = 'Bücher'",
        "record-writer" : "738f484d-a9db-36f8-8817-07c99dde382b",
        "record-reader" : "600c16fd-3584-32ea-bdba-6ec4828f24d8",
        "include-zero-record-flowfiles" : "true",
        "elektronik" : "SELECT *\nFROM FLOWFILE\nWHERE Kategorie = 'Elektronik'",
        "haushalt" : "SELECT *\nFROM FLOWFILE\nWHERE Kategorie = 'Haushalt'",
        "dbf-default-scale" : "0"
      },
      "propertyDescriptors" : {
        "dbf-default-precision" : {
          "displayName" : "Default Decimal Precision",
          "dynamic" : false,
          "identifiesControllerService" : false,
          "name" : "dbf-default-precision",
          "sensitive" : false
        },
        "bücher" : {
          "displayName" : "bücher",
          "dynamic" : true,
          "identifiesControllerService" : false,
          "name" : "bücher",
          "sensitive" : false
        },
        "record-writer" : {
          "displayName" : "Record Writer",
          "dynamic" : false,
          "identifiesControllerService" : true,
          "name" : "record-writer",
          "sensitive" : false
        },
        "record-reader" : {
          "displayName" : "Record Reader",
          "dynamic" : false,
          "identifiesControllerService" : true,
          "name" : "record-reader",
          "sensitive" : false
        },
        "include-zero-record-flowfiles" : {
          "displayName" : "Include Zero Record FlowFiles",
          "dynamic" : false,
          "identifiesControllerService" : false,
          "name" : "include-zero-record-flowfiles",
          "sensitive" : false
        },
        "elektronik" : {
          "displayName" : "elektronik",
          "dynamic" : true,
          "identifiesControllerService" : false,
          "name" : "elektronik",
          "sensitive" : false
        },
        "haushalt" : {
          "displayName" : "haushalt",
          "dynamic" : true,
          "identifiesControllerService" : false,
          "name" : "haushalt",
          "sensitive" : false
        },
        "dbf-default-scale" : {
          "displayName" : "Default Decimal Scale",
          "dynamic" : false,
          "identifiesControllerService" : false,
          "name" : "dbf-default-scale",
          "sensitive" : false
        }
      },
      "retriedRelationships" : [ ],
      "retryCount" : 10,
      "runDurationMillis" : 0,
      "scheduledState" : "ENABLED",
      "schedulingPeriod" : "0 sec",
      "schedulingStrategy" : "TIMER_DRIVEN",
      "style" : { },
      "type" : "org.apache.nifi.processors.standard.QueryRecord",
      "yieldDuration" : "1 sec"
    }, {
      "autoTerminatedRelationships" : [ "failure" ],
      "backoffMechanism" : "PENALIZE_FLOWFILE",
      "bulletinLevel" : "WARN",
      "bundle" : {
        "artifact" : "nifi-standard-nar",
        "group" : "org.apache.nifi",
        "version" : "2.4.0"
      },
      "comments" : "",
      "componentType" : "PROCESSOR",
      "concurrentlySchedulableTaskCount" : 1,
      "executionNode" : "ALL",
      "groupIdentifier" : "flow-contents-group",
      "identifier" : "88cee2df-0198-1000-4c31-20c2257eae39",
      "maxBackoffPeriod" : "10 mins",
      "name" : "Avro to JSON",
      "penaltyDuration" : "30 sec",
      "position" : {
        "x" : 279.83332121240073,
        "y" : -44.166647525521284
      },
      "properties" : {
        "Include Zero Record FlowFiles" : "true",
        "Record Writer" : "738f484d-a9db-36f8-8817-07c99dde382b",
        "Record Reader" : "600c16fd-3584-32ea-bdba-6ec4828f24d8"
      },
      "propertyDescriptors" : {
        "Include Zero Record FlowFiles" : {
          "displayName" : "Include Zero Record FlowFiles",
          "dynamic" : false,
          "identifiesControllerService" : false,
          "name" : "Include Zero Record FlowFiles",
          "sensitive" : false
        },
        "Record Writer" : {
          "displayName" : "Record Writer",
          "dynamic" : false,
          "identifiesControllerService" : true,
          "name" : "Record Writer",
          "sensitive" : false
        },
        "Record Reader" : {
          "displayName" : "Record Reader",
          "dynamic" : false,
          "identifiesControllerService" : true,
          "name" : "Record Reader",
          "sensitive" : false
        }
      },
      "retriedRelationships" : [ ],
      "retryCount" : 10,
      "runDurationMillis" : 0,
      "scheduledState" : "ENABLED",
      "schedulingPeriod" : "0 sec",
      "schedulingStrategy" : "TIMER_DRIVEN",
      "style" : { },
      "type" : "org.apache.nifi.processors.standard.ConvertRecord",
      "yieldDuration" : "1 sec"
    }, {
      "autoTerminatedRelationships" : [ "failure" ],
      "backoffMechanism" : "PENALIZE_FLOWFILE",
      "bulletinLevel" : "WARN",
      "bundle" : {
        "artifact" : "nifi-standard-nar",
        "group" : "org.apache.nifi",
        "version" : "2.4.0"
      },
      "comments" : "",
      "componentType" : "PROCESSOR",
      "concurrentlySchedulableTaskCount" : 1,
      "executionNode" : "ALL",
      "groupIdentifier" : "flow-contents-group",
      "identifier" : "509f3256-c305-39f6-a7a8-eb87bdf3c62d",
      "maxBackoffPeriod" : "10 mins",
      "name" : "ExecuteSQL",
      "penaltyDuration" : "30 sec",
      "position" : {
        "x" : 288.0,
        "y" : -248.0
      },
      "properties" : {
        "esql-max-rows" : "0",
        "dbf-default-precision" : "10",
        "Max Wait Time" : "0 seconds",
        "SQL Query" : "Select * FROM Produkte",
        "Database Connection Pooling Service" : "9d510a56-53df-3c2b-b2ff-4e029be87d1e",
        "esql-auto-commit" : "true",
        "dbf-user-logical-types" : "false",
        "dbf-default-scale" : "0",
        "compression-format" : "NONE",
        "esql-output-batch-size" : "0",
        "esql-fetch-size" : "0",
        "dbf-normalize" : "false",
        "Content Output Strategy" : "EMPTY"
      },
      "propertyDescriptors" : {
        "esql-max-rows" : {
          "displayName" : "Max Rows Per Flow File",
          "dynamic" : false,
          "identifiesControllerService" : false,
          "name" : "esql-max-rows",
          "sensitive" : false
        },
        "dbf-default-precision" : {
          "displayName" : "Default Decimal Precision",
          "dynamic" : false,
          "identifiesControllerService" : false,
          "name" : "dbf-default-precision",
          "sensitive" : false
        },
        "Max Wait Time" : {
          "displayName" : "Max Wait Time",
          "dynamic" : false,
          "identifiesControllerService" : false,
          "name" : "Max Wait Time",
          "sensitive" : false
        },
        "SQL Query" : {
          "displayName" : "SQL Query",
          "dynamic" : false,
          "identifiesControllerService" : false,
          "name" : "SQL Query",
          "sensitive" : false
        },
        "Database Connection Pooling Service" : {
          "displayName" : "Database Connection Pooling Service",
          "dynamic" : false,
          "identifiesControllerService" : true,
          "name" : "Database Connection Pooling Service",
          "sensitive" : false
        },
        "sql-post-query" : {
          "displayName" : "SQL Post-Query",
          "dynamic" : false,
          "identifiesControllerService" : false,
          "name" : "sql-post-query",
          "sensitive" : false
        },
        "esql-auto-commit" : {
          "displayName" : "Set Auto Commit",
          "dynamic" : false,
          "identifiesControllerService" : false,
          "name" : "esql-auto-commit",
          "sensitive" : false
        },
        "dbf-user-logical-types" : {
          "displayName" : "Use Avro Logical Types",
          "dynamic" : false,
          "identifiesControllerService" : false,
          "name" : "dbf-user-logical-types",
          "sensitive" : false
        },
        "dbf-default-scale" : {
          "displayName" : "Default Decimal Scale",
          "dynamic" : false,
          "identifiesControllerService" : false,
          "name" : "dbf-default-scale",
          "sensitive" : false
        },
        "sql-pre-query" : {
          "displayName" : "SQL Pre-Query",
          "dynamic" : false,
          "identifiesControllerService" : false,
          "name" : "sql-pre-query",
          "sensitive" : false
        },
        "compression-format" : {
          "displayName" : "Compression Format",
          "dynamic" : false,
          "identifiesControllerService" : false,
          "name" : "compression-format",
          "sensitive" : false
        },
        "esql-output-batch-size" : {
          "displayName" : "Output Batch Size",
          "dynamic" : false,
          "identifiesControllerService" : false,
          "name" : "esql-output-batch-size",
          "sensitive" : false
        },
        "esql-fetch-size" : {
          "displayName" : "Fetch Size",
          "dynamic" : false,
          "identifiesControllerService" : false,
          "name" : "esql-fetch-size",
          "sensitive" : false
        },
        "dbf-normalize" : {
          "displayName" : "Normalize Table/Column Names",
          "dynamic" : false,
          "identifiesControllerService" : false,
          "name" : "dbf-normalize",
          "sensitive" : false
        },
        "Content Output Strategy" : {
          "displayName" : "Content Output Strategy",
          "dynamic" : false,
          "identifiesControllerService" : false,
          "name" : "Content Output Strategy",
          "sensitive" : false
        }
      },
      "retriedRelationships" : [ ],
      "retryCount" : 10,
      "runDurationMillis" : 0,
      "scheduledState" : "ENABLED",
      "schedulingPeriod" : "0 sec",
      "schedulingStrategy" : "TIMER_DRIVEN",
      "style" : { },
      "type" : "org.apache.nifi.processors.standard.ExecuteSQL",
      "yieldDuration" : "1 sec"
    } ],
    "remoteProcessGroups" : [ ],
    "scheduledState" : "ENABLED",
    "statelessFlowTimeout" : "1 min"
  },
  "flowEncodingVersion" : "1.0",
  "latest" : false,
  "parameterContexts" : { },
  "parameterProviders" : { },
  "snapshotMetadata" : {
    "author" : "mhl_admin",
    "flowIdentifier" : "product-data-routing",
    "timestamp" : 0
  }
}